power_models_wrapper/__init__.py
power_models_wrapper/formulation_type.py
power_models_wrapper/julia_preparation.py
power_models_wrapper/optimal_power_flow.py
power_models_wrapper/remote_off_grid.py
power_models_wrapper/solver_enum.py
power_models_wrapper/version.py
power_models_wrapper/csv/__init__.py
power_models_wrapper/csv/aggregate_csv_generator.py
power_models_wrapper/csv/csv_generation_manager.py
power_models_wrapper/csv/csv_generator.py
power_models_wrapper/csv/section/__init__.py
power_models_wrapper/csv/section/aggregate_summary_section_generator.py
power_models_wrapper/csv/section/new_lines_section_generator.py
power_models_wrapper/csv/section/summary_section_generator.py
power_models_wrapper/csv/section/timeseries_section_generator.py
power_models_wrapper/data_transformation/__init__.py
power_models_wrapper/data_transformation/abstract_filter.py
power_models_wrapper/data_transformation/accumulation_filter.py
power_models_wrapper/data_transformation/all_pass_filter.py
power_models_wrapper/data_transformation/usage_filter.py
power_models_wrapper-0.4.1.dist-info/DESCRIPTION.rst
power_models_wrapper-0.4.1.dist-info/METADATA
power_models_wrapper-0.4.1.dist-info/RECORD
power_models_wrapper-0.4.1.dist-info/WHEEL
power_models_wrapper-0.4.1.dist-info/metadata.json
power_models_wrapper-0.4.1.dist-info/top_level.txt
tests/power_models_wrapper/__init__.py
tests/power_models_wrapper/test_optimal_power_flow.py
tests/power_models_wrapper/test_remote_off_grid.py
