Metadata-Version: 2.0
Name: power-models-wrapper
Version: 0.4.1
Summary: Python wrapper to use Julia PowerModels
Home-page: UNKNOWN
Author: Tadatoshi Takahashi
Author-email: tadatoshi@lbl.gov
License: UNKNOWN
Keywords: optimization engineering
Platform: UNKNOWN
Classifier: Development Status :: 3 - Alpha
Classifier: Intended Audience :: Developers
Classifier: Topic :: Scientific/Engineering
Classifier: License :: OSI Approved :: MIT License
Classifier: Programming Language :: Python :: 3.6
Requires-Dist: numpy
Requires-Dist: scipy
Requires-Dist: matplotlib
Requires-Dist: pandas
Requires-Dist: julia
Requires-Dist: xlrd
